crono/__init__.py
crono/api.py
crono/job.py
crono/queue.py
crono/tasks.py
crono/triggers.py
crono/utils.py
crono-0.1.8.dist-info/LICENSE
crono-0.1.8.dist-info/METADATA
crono-0.1.8.dist-info/WHEEL
crono-0.1.8.dist-info/top_level.txt
crono-0.1.8.dist-info/RECORD
